behave_manners/__init__.py
behave_manners/action_chains.py
behave_manners/alt_parser.py
behave_manners/context.py
behave_manners/downloads.py
behave_manners/dpo_run_browser.py
behave_manners/dpo_validator.py
behave_manners/screenshots.py
behave_manners/site.py
behave_manners/site_setup.py
behave_manners/step_utils.py
behave_manners/pagelems/__init__.py
behave_manners/pagelems/actions.py
behave_manners/pagelems/base_parsers.py
behave_manners/pagelems/dom_components.py
behave_manners/pagelems/dom_descriptors.py
behave_manners/pagelems/dom_meta.py
behave_manners/pagelems/exceptions.py
behave_manners/pagelems/filter_components.py
behave_manners/pagelems/helpers.py
behave_manners/pagelems/index_elems.py
behave_manners/pagelems/loaders.py
behave_manners/pagelems/main.py
behave_manners/pagelems/page_elements.py
behave_manners/pagelems/scopes.py
behave_manners/pagelems/site_collection.py
behave_manners/steplib/__init__.py
behave_manners/steplib/run_bg_devel.py
behave_manners-0.14.0.dist-info/LICENSE
behave_manners-0.14.0.dist-info/METADATA
behave_manners-0.14.0.dist-info/WHEEL
behave_manners-0.14.0.dist-info/entry_points.txt
behave_manners-0.14.0.dist-info/top_level.txt
behave_manners-0.14.0.dist-info/zip-safe
behave_manners-0.14.0.dist-info/RECORD
