Metadata-Version: 2.1
Name: behave-manners
Version: 0.14.0
Summary: A layer of abstraction on top of behave for web-UI testing, designed to handle complexity of large sites
Home-page: http://github.com/xrg/behave_manners
Author: Panos Christeas
Author-email: xrg@pefnos.com
License: BSD-2-Clause
Platform: UNKNOWN
Classifier: Development Status :: 3 - Alpha
Classifier: Environment :: Console
Classifier: Intended Audience :: Developers
Classifier: Operating System :: OS Independent
Classifier: Programming Language :: Python :: 2
Classifier: Programming Language :: Python :: 2.6
Classifier: Programming Language :: Python :: 2.7
Classifier: Programming Language :: Python :: 3
Classifier: Programming Language :: Python :: 3.5
Classifier: Programming Language :: Python :: 3.6
Classifier: Topic :: Software Development :: Testing
Classifier: License :: OSI Approved :: BSD License
Provides: behave_manners
Requires-Dist: behave (>=1.2.6)
Requires-Dist: f3utils
Requires-Dist: pyyaml
Requires-Dist: selenium
Provides-Extra: develop
